<?xml version="1.0" encoding="UTF-8"?><personas><personas><nombre>ALBERT</nombre><apellidos>MARTIN VICENTE</apellidos><email>amartinvicente@iesvdc.com</email><numeroDNI>18707923</numeroDNI><letraDNI>E</letraDNI><fechaNacimiento>1957-05-02</fechaNacimiento><sexo>HOMBRE</sexo></personas><personas><nombre>JOSE IGNACIO</nombre><apellidos>ROJAS BRAVO</apellidos><email>jrojasbravo@iesvdc.com</email><numeroDNI>63558822</numeroDNI><letraDNI>R</letraDNI><fechaNacimiento>2015-08-23</fechaNacimiento><sexo>MUJER</sexo></personas><personas><nombre>IVAN</nombre><apellidos>PEREZ IGLESIAS</apellidos><email>ipereziglesias@iesvdc.com</email><numeroDNI>58617528</numeroDNI><letraDNI>G</letraDNI><fechaNacimiento>1999-06-23</fechaNacimiento><sexo>HOMBRE</sexo></personas><personas><nombre>EMILIO</nombre><apellidos>AGUILAR GARRIDO</apellidos><email>eaguilargarrido@iesvdc.com</email><numeroDNI>46174178</numeroDNI><letraDNI>E</letraDNI><fechaNacimiento>2005-01-10</fechaNacimiento><sexo>PND</sexo></personas><personas><nombre>SANTIAGO</nombre><apellidos>HERRERA REYES</apellidos><email>sherrerareyes@iesvdc.com</email><numeroDNI>38718627</numeroDNI><letraDNI>J</letraDNI><fechaNacimiento>1934-06-24</fechaNacimiento><sexo>HOMBRE</sexo></personas><personas><nombre>ALEX</nombre><apellidos>ORTIZ VAZQUEZ</apellidos><email>aortizvazquez@iesvdc.com</email><numeroDNI>43207567</numeroDNI><letraDNI>C</letraDNI><fechaNacimiento>2008-09-22</fechaNacimiento><sexo>HOMBRE</sexo></personas><personas><nombre>JUAN</nombre><apellidos>GONZALEZ SANZ</apellidos><email>jgonzalezsanz@iesvdc.com</email><numeroDNI>64056694</numeroDNI><letraDNI>S</letraDNI><fechaNacimiento>1955-06-11</fechaNacimiento><sexo>MUJER</sexo></personas><personas><nombre>ENRIQUE</nombre><apellidos>SAEZ MARTIN</apellidos><email>esaezmartin@iesvdc.com</email><numeroDNI>58460663</numeroDNI><letraDNI>E</letraDNI><fechaNacimiento>1956-09-17</fechaNacimiento><sexo>HOMBRE</sexo></personas><personas><nombre>JUAN MANUEL</nombre><apellidos>VICENTE PEREZ</apellidos><email>jvicenteperez@iesvdc.com</email><numeroDNI>80476358</numeroDNI><letraDNI>W</letraDNI><fechaNacimiento>2023-12-20</fechaNacimiento><sexo>HOMBRE</sexo></personas><personas><nombre>MANUEL</nombre><apellidos>CANO CASTRO</apellidos><email>mcanocastro@iesvdc.com</email><numeroDNI>59967063</numeroDNI><letraDNI>Z</letraDNI><fechaNacimiento>1925-11-05</fechaNacimiento><sexo>PND</sexo></personas><personas><nombre>MARIO</nombre><apellidos>PRIETO PARRA</apellidos><email>mprietoparra@iesvdc.com</email><numeroDNI>79106347</numeroDNI><letraDNI>D</letraDNI><fechaNacimiento>2023-04-14</fechaNacimiento><sexo>HOMBRE</sexo></personas><personas><nombre>SALVADOR</nombre><apellidos>JIMENEZ CAMPOS</apellidos><email>sjimenezcampos@iesvdc.com</email><numeroDNI>18031946</numeroDNI><letraDNI>S</letraDNI><fechaNacimiento>1930-03-02</fechaNacimiento><sexo>HOMBRE</sexo></personas><personas><nombre>ANDRES</nombre><apellidos>SANTIAGO CAMPOS</apellidos><email>asantiagocampos@iesvdc.com</email><numeroDNI>71595003</numeroDNI><letraDNI>M</letraDNI><fechaNacimiento>1953-02-04</fechaNacimiento><sexo>MUJER</sexo></personas><personas><nombre>JOSE FRANCISCO</nombre><apellidos>RUBIO SANTANA</apellidos><email>jrubiosantana@iesvdc.com</email><numeroDNI>75178349</numeroDNI><letraDNI>C</letraDNI><fechaNacimiento>1934-11-19</fechaNacimiento><sexo>HOMBRE</sexo></personas><personas><nombre>MARC</nombre><apellidos>FUENTES SILVA</apellidos><email>mfuentessilva@iesvdc.com</email><numeroDNI>89544849</numeroDNI><letraDNI>F</letraDNI><fechaNacimiento>1978-03-25</fechaNacimiento><sexo>PND</sexo></personas><personas><nombre>VICTOR MANUEL</nombre><apellidos>CRESPO SANTIAGO</apellidos><email>vcresposantiago@iesvdc.com</email><numeroDNI>13325742</numeroDNI><letraDNI>W</letraDNI><fechaNacimiento>1987-11-19</fechaNacimiento><sexo>MUJER</sexo></personas><personas><nombre>JOSE MIGUEL</nombre><apellidos>SANTANA VELASCO</apellidos><email>jsantanavelasco@iesvdc.com</email><numeroDNI>24773027</numeroDNI><letraDNI>A</letraDNI><fechaNacimiento>2003-05-12</fechaNacimiento><sexo>PND</sexo></personas><personas><nombre>MANUEL</nombre><apellidos>SANTIAGO GALLEGO</apellidos><email>msantiagogallego@iesvdc.com</email><numeroDNI>71732350</numeroDNI><letraDNI>L</letraDNI><fechaNacimiento>2023-05-04</fechaNacimiento><sexo>PND</sexo></personas><personas><nombre>RAFAEL</nombre><apellidos>IBAÑEZ GIMENEZ</apellidos><email>ribanezgimenez@iesvdc.com</email><numeroDNI>33696646</numeroDNI><letraDNI>J</letraDNI><fechaNacimiento>1934-05-18</fechaNacimiento><sexo>MUJER</sexo></personas><personas><nombre>IGNACIO</nombre><apellidos>LOZANO MARQUEZ</apellidos><email>ilozanomarquez@iesvdc.com</email><numeroDNI>61974368</numeroDNI><letraDNI>V</letraDNI><fechaNacimiento>1995-08-21</fechaNacimiento><sexo>HOMBRE</sexo></personas><personas><nombre>RICARDO</nombre><apellidos>IBAÑEZ RIVERA</apellidos><email>ribanezrivera@iesvdc.com</email><numeroDNI>20159161</numeroDNI><letraDNI>Y</letraDNI><fechaNacimiento>2005-03-12</fechaNacimiento><sexo>MUJER</sexo></personas><personas><nombre>MARTIN</nombre><apellidos>FERNANDEZ BRAVO</apellidos><email>mfernandezbravo@iesvdc.com</email><numeroDNI>62803248</numeroDNI><letraDNI>T</letraDNI><fechaNacimiento>2013-09-22</fechaNacimiento><sexo>HOMBRE</sexo></personas><personas><nombre>JOSE ANTONIO</nombre><apellidos>PARRA LOZANO</apellidos><email>jparralozano@iesvdc.com</email><numeroDNI>74915224</numeroDNI><letraDNI>S</letraDNI><fechaNacimiento>1924-06-04</fechaNacimiento><sexo>PND</sexo></personas><personas><nombre>MARCOS</nombre><apellidos>DIEZ GOMEZ</apellidos><email>mdiezgomez@iesvdc.com</email><numeroDNI>94476124</numeroDNI><letraDNI>J</letraDNI><fechaNacimiento>1999-02-17</fechaNacimiento><sexo>MUJER</sexo></personas><personas><nombre>JUAN</nombre><apellidos>ARIAS SANZ</apellidos><email>jariassanz@iesvdc.com</email><numeroDNI>72368151</numeroDNI><letraDNI>P</letraDNI><fechaNacimiento>1940-09-01</fechaNacimiento><sexo>MUJER</sexo></personas><personas><nombre>SALVADOR</nombre><apellidos>TORRES RODRIGUEZ</apellidos><email>storresrodriguez@iesvdc.com</email><numeroDNI>51951260</numeroDNI><letraDNI>X</letraDNI><fechaNacimiento>2024-07-27</fechaNacimiento><sexo>MUJER</sexo></personas><personas><nombre>JOSE LUIS</nombre><apellidos>DELGADO GALLEGO</apellidos><email>jdelgadogallego@iesvdc.com</email><numeroDNI>76066221</numeroDNI><letraDNI>T</letraDNI><fechaNacimiento>1950-10-29</fechaNacimiento><sexo>HOMBRE</sexo></personas><personas><nombre>ALFREDO</nombre><apellidos>VIDAL PASTOR</apellidos><email>avidalpastor@iesvdc.com</email><numeroDNI>94366427</numeroDNI><letraDNI>A</letraDNI><fechaNacimiento>2023-06-26</fechaNacimiento><sexo>HOMBRE</sexo></personas><personas><nombre>JOSE CARLOS</nombre><apellidos>CASTILLO CANO</apellidos><email>jcastillocano@iesvdc.com</email><numeroDNI>66378065</numeroDNI><letraDNI>L</letraDNI><fechaNacimiento>1959-01-23</fechaNacimiento><sexo>MUJER</sexo></personas><personas><nombre>JOSE LUIS</nombre><apellidos>PEREZ CORTES</apellidos><email>jperezcortes@iesvdc.com</email><numeroDNI>15140602</numeroDNI><letraDNI>R</letraDNI><fechaNacimiento>1929-12-17</fechaNacimiento><sexo>PND</sexo></personas><personas><nombre>DIEGO</nombre><apellidos>CABRERA MUÑOZ</apellidos><email>dcabreramunoz@iesvdc.com</email><numeroDNI>45657979</numeroDNI><letraDNI>N</letraDNI><fechaNacimiento>1954-10-31</fechaNacimiento><sexo>MUJER</sexo></personas><personas><nombre>RAMON</nombre><apellidos>FERRER DURAN</apellidos><email>rferrerduran@iesvdc.com</email><numeroDNI>17039427</numeroDNI><letraDNI>S</letraDNI><fechaNacimiento>1947-12-16</fechaNacimiento><sexo>HOMBRE</sexo></personas><personas><nombre>JUAN FRANCISCO</nombre><apellidos>HERRERA VIDAL</apellidos><email>jherreravidal@iesvdc.com</email><numeroDNI>51794977</numeroDNI><letraDNI>N</letraDNI><fechaNacimiento>2012-07-07</fechaNacimiento><sexo>PND</sexo></personas><personas><nombre>RAFAEL</nombre><apellidos>TORRES CARRASCO</apellidos><email>rtorrescarrasco@iesvdc.com</email><numeroDNI>78741474</numeroDNI><letraDNI>P</letraDNI><fechaNacimiento>1945-09-03</fechaNacimiento><sexo>MUJER</sexo></personas><personas><nombre>ANTONIO</nombre><apellidos>RAMOS AGUILAR</apellidos><email>aramosaguilar@iesvdc.com</email><numeroDNI>34339530</numeroDNI><letraDNI>R</letraDNI><fechaNacimiento>2013-11-17</fechaNacimiento><sexo>PND</sexo></personas><personas><nombre>PAU</nombre><apellidos>RAMIREZ GIL</apellidos><email>pramirezgil@iesvdc.com</email><numeroDNI>44171937</numeroDNI><letraDNI>T</letraDNI><fechaNacimiento>1959-01-19</fechaNacimiento><sexo>PND</sexo></personas><personas><nombre>JAVIER</nombre><apellidos>VIDAL HIDALGO</apellidos><email>jvidalhidalgo@iesvdc.com</email><numeroDNI>22417520</numeroDNI><letraDNI>H</letraDNI><fechaNacimiento>1985-09-02</fechaNacimiento><sexo>MUJER</sexo></personas><personas><nombre>SERGIO</nombre><apellidos>NIETO MARIN</apellidos><email>snietomarin@iesvdc.com</email><numeroDNI>18362895</numeroDNI><letraDNI>V</letraDNI><fechaNacimiento>1926-08-12</fechaNacimiento><sexo>MUJER</sexo></personas><personas><nombre>MIGUEL</nombre><apellidos>MORENO MORENO</apellidos><email>mmorenomoreno@iesvdc.com</email><numeroDNI>49728530</numeroDNI><letraDNI>T</letraDNI><fechaNacimiento>1968-11-27</fechaNacimiento><sexo>PND</sexo></personas><personas><nombre>ALBERT</nombre><apellidos>VIDAL SANTOS</apellidos><email>avidalsantos@iesvdc.com</email><numeroDNI>71645417</numeroDNI><letraDNI>A</letraDNI><fechaNacimiento>1961-10-07</fechaNacimiento><sexo>PND</sexo></personas><personas><nombre>CRISTIAN</nombre><apellidos>RODRIGUEZ VARGAS</apellidos><email>crodriguezvargas@iesvdc.com</email><numeroDNI>81806287</numeroDNI><letraDNI>W</letraDNI><fechaNacimiento>2019-06-02</fechaNacimiento><sexo>PND</sexo></personas><personas><nombre>VICTOR</nombre><apellidos>MARTIN DELGADO</apellidos><email>vmartindelgado@iesvdc.com</email><numeroDNI>67038985</numeroDNI><letraDNI>B</letraDNI><fechaNacimiento>1951-06-17</fechaNacimiento><sexo>MUJER</sexo></personas><personas><nombre>MARTIN</nombre><apellidos>IGLESIAS MARQUEZ</apellidos><email>miglesiasmarquez@iesvdc.com</email><numeroDNI>47549600</numeroDNI><letraDNI>K</letraDNI><fechaNacimiento>1990-08-17</fechaNacimiento><sexo>MUJER</sexo></personas><personas><nombre>IVAN</nombre><apellidos>HIDALGO SANTIAGO</apellidos><email>ihidalgosantiago@iesvdc.com</email><numeroDNI>55312617</numeroDNI><letraDNI>D</letraDNI><fechaNacimiento>2006-09-24</fechaNacimiento><sexo>MUJER</sexo></personas><personas><nombre>JORDI</nombre><apellidos>BENITEZ ORTEGA</apellidos><email>jbenitezortega@iesvdc.com</email><numeroDNI>34436695</numeroDNI><letraDNI>Z</letraDNI><fechaNacimiento>1955-01-26</fechaNacimiento><sexo>HOMBRE</sexo></personas><personas><nombre>JUAN MANUEL</nombre><apellidos>DOMINGUEZ CASTILLO</apellidos><email>jdominguezcastillo@iesvdc.com</email><numeroDNI>81200180</numeroDNI><letraDNI>Z</letraDNI><fechaNacimiento>1935-12-30</fechaNacimiento><sexo>HOMBRE</sexo></personas><personas><nombre>JOSE FRANCISCO</nombre><apellidos>CORTES FUENTES</apellidos><email>jcortesfuentes@iesvdc.com</email><numeroDNI>70808294</numeroDNI><letraDNI>B</letraDNI><fechaNacimiento>1973-12-27</fechaNacimiento><sexo>HOMBRE</sexo></personas><personas><nombre>HUGO</nombre><apellidos>REYES VEGA</apellidos><email>hreyesvega@iesvdc.com</email><numeroDNI>63570122</numeroDNI><letraDNI>P</letraDNI><fechaNacimiento>1979-12-22</fechaNacimiento><sexo>PND</sexo></personas><personas><nombre>HUGO</nombre><apellidos>ORTIZ MARQUEZ</apellidos><email>hortizmarquez@iesvdc.com</email><numeroDNI>81035005</numeroDNI><letraDNI>W</letraDNI><fechaNacimiento>1946-02-11</fechaNacimiento><sexo>MUJER</sexo></personas><personas><nombre>ALBERTO</nombre><apellidos>SAEZ ORTIZ</apellidos><email>asaezortiz@iesvdc.com</email><numeroDNI>82671509</numeroDNI><letraDNI>X</letraDNI><fechaNacimiento>1962-10-17</fechaNacimiento><sexo>MUJER</sexo></personas><personas><nombre>LUIS</nombre><apellidos>LOZANO SAEZ</apellidos><email>llozanosaez@iesvdc.com</email><numeroDNI>90328959</numeroDNI><letraDNI>R</letraDNI><fechaNacimiento>1932-08-29</fechaNacimiento><sexo>HOMBRE</sexo></personas><personas><nombre>VICTOR MANUEL</nombre><apellidos>CASTILLO SANZ</apellidos><email>vcastillosanz@iesvdc.com</email><numeroDNI>88201955</numeroDNI><letraDNI>Z</letraDNI><fechaNacimiento>1991-04-22</fechaNacimiento><sexo>PND</sexo></personas><personas><nombre>VICTOR MANUEL</nombre><apellidos>PEÑA SILVA</apellidos><email>vpenasilva@iesvdc.com</email><numeroDNI>38084686</numeroDNI><letraDNI>K</letraDNI><fechaNacimiento>1967-09-23</fechaNacimiento><sexo>PND</sexo></personas><personas><nombre>TOMAS</nombre><apellidos>GONZALEZ VARGAS</apellidos><email>tgonzalezvargas@iesvdc.com</email><numeroDNI>91797510</numeroDNI><letraDNI>W</letraDNI><fechaNacimiento>1988-02-22</fechaNacimiento><sexo>MUJER</sexo></personas><personas><nombre>OSCAR</nombre><apellidos>MOYA VICENTE</apellidos><email>omoyavicente@iesvdc.com</email><numeroDNI>89546591</numeroDNI><letraDNI>R</letraDNI><fechaNacimiento>1925-10-03</fechaNacimiento><sexo>MUJER</sexo></personas><personas><nombre>MARTIN</nombre><apellidos>CARMONA IGLESIAS</apellidos><email>mcarmonaiglesias@iesvdc.com</email><numeroDNI>97803963</numeroDNI><letraDNI>M</letraDNI><fechaNacimiento>1955-01-13</fechaNacimiento><sexo>PND</sexo></personas><personas><nombre>JOSE LUIS</nombre><apellidos>NUÑEZ ORTIZ</apellidos><email>jnunezortiz@iesvdc.com</email><numeroDNI>74406572</numeroDNI><letraDNI>P</letraDNI><fechaNacimiento>1994-06-27</fechaNacimiento><sexo>HOMBRE</sexo></personas><personas><nombre>ROBERTO</nombre><apellidos>DELGADO VEGA</apellidos><email>rdelgadovega@iesvdc.com</email><numeroDNI>91575722</numeroDNI><letraDNI>A</letraDNI><fechaNacimiento>1954-06-17</fechaNacimiento><sexo>HOMBRE</sexo></personas><personas><nombre>FERNANDO</nombre><apellidos>RODRIGUEZ DELGADO</apellidos><email>frodriguezdelgado@iesvdc.com</email><numeroDNI>41182258</numeroDNI><letraDNI>E</letraDNI><fechaNacimiento>2011-04-20</fechaNacimiento><sexo>HOMBRE</sexo></personas><personas><nombre>MARIANO</nombre><apellidos>MARTIN PEÑA</apellidos><email>mmartinpena@iesvdc.com</email><numeroDNI>61251506</numeroDNI><letraDNI>E</letraDNI><fechaNacimiento>2010-07-03</fechaNacimiento><sexo>PND</sexo></personas><personas><nombre>JESUS</nombre><apellidos>SILVA RUBIO</apellidos><email>jsilvarubio@iesvdc.com</email><numeroDNI>99674220</numeroDNI><letraDNI>V</letraDNI><fechaNacimiento>2004-02-21</fechaNacimiento><sexo>HOMBRE</sexo></personas><personas><nombre>RODRIGO</nombre><apellidos>CANO MOYA</apellidos><email>rcanomoya@iesvdc.com</email><numeroDNI>84952569</numeroDNI><letraDNI>E</letraDNI><fechaNacimiento>1991-11-11</fechaNacimiento><sexo>HOMBRE</sexo></personas><personas><nombre>JORDI</nombre><apellidos>GALLEGO NUÑEZ</apellidos><email>jgallegonunez@iesvdc.com</email><numeroDNI>29706933</numeroDNI><letraDNI>H</letraDNI><fechaNacimiento>1954-05-04</fechaNacimiento><sexo>HOMBRE</sexo></personas><personas><nombre>DANIEL</nombre><apellidos>SUAREZ ORTEGA</apellidos><email>dsuarezortega@iesvdc.com</email><numeroDNI>55666052</numeroDNI><letraDNI>A</letraDNI><fechaNacimiento>1991-08-21</fechaNacimiento><sexo>MUJER</sexo></personas><personas><nombre>JAIME</nombre><apellidos>SANTOS FERNANDEZ</apellidos><email>jsantosfernandez@iesvdc.com</email><numeroDNI>25290006</numeroDNI><letraDNI>B</letraDNI><fechaNacimiento>2022-03-15</fechaNacimiento><sexo>MUJER</sexo></personas><personas><nombre>JOSE MANUEL</nombre><apellidos>VELASCO GONZALEZ</apellidos><email>jvelascogonzalez@iesvdc.com</email><numeroDNI>13433400</numeroDNI><letraDNI>C</letraDNI><fechaNacimiento>1952-08-05</fechaNacimiento><sexo>PND</sexo></personas><personas><nombre>DAVID</nombre><apellidos>IBAÑEZ PASCUAL</apellidos><email>dibanezpascual@iesvdc.com</email><numeroDNI>60464760</numeroDNI><letraDNI>Z</letraDNI><fechaNacimiento>2000-10-02</fechaNacimiento><sexo>HOMBRE</sexo></personas><personas><nombre>TOMAS</nombre><apellidos>DURAN SILVA</apellidos><email>tduransilva@iesvdc.com</email><numeroDNI>19057700</numeroDNI><letraDNI>S</letraDNI><fechaNacimiento>2017-07-02</fechaNacimiento><sexo>HOMBRE</sexo></personas><personas><nombre>XAVIER</nombre><apellidos>DIAZ ALVAREZ</apellidos><email>xdiazalvarez@iesvdc.com</email><numeroDNI>21614483</numeroDNI><letraDNI>A</letraDNI><fechaNacimiento>2021-12-25</fechaNacimiento><sexo>HOMBRE</sexo></personas><personas><nombre>JAVIER</nombre><apellidos>LOZANO CALVO</apellidos><email>jlozanocalvo@iesvdc.com</email><numeroDNI>26859101</numeroDNI><letraDNI>T</letraDNI><fechaNacimiento>1927-11-19</fechaNacimiento><sexo>MUJER</sexo></personas><personas><nombre>MARCOS</nombre><apellidos>VEGA GALLEGO</apellidos><email>mvegagallego@iesvdc.com</email><numeroDNI>61200541</numeroDNI><letraDNI>W</letraDNI><fechaNacimiento>1990-06-05</fechaNacimiento><sexo>MUJER</sexo></personas><personas><nombre>JOSE</nombre><apellidos>LORENZO SANTOS</apellidos><email>jlorenzosantos@iesvdc.com</email><numeroDNI>37921711</numeroDNI><letraDNI>R</letraDNI><fechaNacimiento>2016-03-09</fechaNacimiento><sexo>MUJER</sexo></personas><personas><nombre>LUCAS</nombre><apellidos>BENITEZ DIEZ</apellidos><email>lbenitezdiez@iesvdc.com</email><numeroDNI>89534016</numeroDNI><letraDNI>F</letraDNI><fechaNacimiento>1993-04-04</fechaNacimiento><sexo>PND</sexo></personas><personas><nombre>JOSE FRANCISCO</nombre><apellidos>FERRER JIMENEZ</apellidos><email>jferrerjimenez@iesvdc.com</email><numeroDNI>85709185</numeroDNI><letraDNI>F</letraDNI><fechaNacimiento>1943-09-23</fechaNacimiento><sexo>MUJER</sexo></personas><personas><nombre>MIGUEL</nombre><apellidos>GARCIA GARRIDO</apellidos><email>mgarciagarrido@iesvdc.com</email><numeroDNI>83505927</numeroDNI><letraDNI>B</letraDNI><fechaNacimiento>2019-04-24</fechaNacimiento><sexo>PND</sexo></personas><personas><nombre>MIGUEL</nombre><apellidos>MONTERO MORALES</apellidos><email>mmonteromorales@iesvdc.com</email><numeroDNI>81553992</numeroDNI><letraDNI>V</letraDNI><fechaNacimiento>2016-05-09</fechaNacimiento><sexo>HOMBRE</sexo></personas><personas><nombre>DIEGO</nombre><apellidos>FERNANDEZ BENITEZ</apellidos><email>dfernandezbenitez@iesvdc.com</email><numeroDNI>89187001</numeroDNI><letraDNI>Q</letraDNI><fechaNacimiento>1926-08-18</fechaNacimiento><sexo>MUJER</sexo></personas><personas><nombre>FRANCISCO JOSE</nombre><apellidos>SANTIAGO VAZQUEZ</apellidos><email>fsantiagovazquez@iesvdc.com</email><numeroDNI>26816284</numeroDNI><letraDNI>D</letraDNI><fechaNacimiento>1974-12-26</fechaNacimiento><sexo>MUJER</sexo></personas><personas><nombre>RUBEN</nombre><apellidos>PASTOR DOMINGUEZ</apellidos><email>rpastordominguez@iesvdc.com</email><numeroDNI>76124422</numeroDNI><letraDNI>B</letraDNI><fechaNacimiento>1988-03-13</fechaNacimiento><sexo>HOMBRE</sexo></personas><personas><nombre>TOMAS</nombre><apellidos>CAMPOS ALONSO</apellidos><email>tcamposalonso@iesvdc.com</email><numeroDNI>24169235</numeroDNI><letraDNI>F</letraDNI><fechaNacimiento>2023-10-27</fechaNacimiento><sexo>PND</sexo></personas><personas><nombre>ENRIQUE</nombre><apellidos>GUERRERO GALLARDO</apellidos><email>eguerrerogallardo@iesvdc.com</email><numeroDNI>70698932</numeroDNI><letraDNI>Z</letraDNI><fechaNacimiento>1987-06-06</fechaNacimiento><sexo>MUJER</sexo></personas><personas><nombre>MANUEL</nombre><apellidos>FERNANDEZ CARRASCO</apellidos><email>mfernandezcarrasco@iesvdc.com</email><numeroDNI>90160050</numeroDNI><letraDNI>G</letraDNI><fechaNacimiento>1988-01-30</fechaNacimiento><sexo>HOMBRE</sexo></personas><personas><nombre>MOHAMED</nombre><apellidos>GARCIA CRESPO</apellidos><email>mgarciacrespo@iesvdc.com</email><numeroDNI>92396555</numeroDNI><letraDNI>N</letraDNI><fechaNacimiento>1941-10-25</fechaNacimiento><sexo>HOMBRE</sexo></personas><personas><nombre>VICTOR MANUEL</nombre><apellidos>SANTIAGO SILVA</apellidos><email>vsantiagosilva@iesvdc.com</email><numeroDNI>39617898</numeroDNI><letraDNI>F</letraDNI><fechaNacimiento>1937-05-07</fechaNacimiento><sexo>HOMBRE</sexo></personas><personas><nombre>SANTIAGO</nombre><apellidos>PASTOR DOMINGUEZ</apellidos><email>spastordominguez@iesvdc.com</email><numeroDNI>35713363</numeroDNI><letraDNI>K</letraDNI><fechaNacimiento>2015-07-20</fechaNacimiento><sexo>PND</sexo></personas><personas><nombre>JAVIER</nombre><apellidos>GARCIA REYES</apellidos><email>jgarciareyes@iesvdc.com</email><numeroDNI>60428399</numeroDNI><letraDNI>Q</letraDNI><fechaNacimiento>1995-04-22</fechaNacimiento><sexo>HOMBRE</sexo></personas><personas><nombre>JUAN FRANCISCO</nombre><apellidos>MORALES DOMINGUEZ</apellidos><email>jmoralesdominguez@iesvdc.com</email><numeroDNI>28633029</numeroDNI><letraDNI>F</letraDNI><fechaNacimiento>1940-03-05</fechaNacimiento><sexo>HOMBRE</sexo></personas><personas><nombre>JOSE MANUEL</nombre><apellidos>MORA DELGADO</apellidos><email>jmoradelgado@iesvdc.com</email><numeroDNI>78607687</numeroDNI><letraDNI>N</letraDNI><fechaNacimiento>1983-11-14</fechaNacimiento><sexo>MUJER</sexo></personas><personas><nombre>JULIAN</nombre><apellidos>CABRERA CASTILLO</apellidos><email>jcabreracastillo@iesvdc.com</email><numeroDNI>32563867</numeroDNI><letraDNI>F</letraDNI><fechaNacimiento>1990-03-15</fechaNacimiento><sexo>PND</sexo></personas><personas><nombre>LUIS</nombre><apellidos>ALONSO CASTRO</apellidos><email>lalonsocastro@iesvdc.com</email><numeroDNI>41628791</numeroDNI><letraDNI>X</letraDNI><fechaNacimiento>1955-06-20</fechaNacimiento><sexo>HOMBRE</sexo></personas><personas><nombre>ANGEL</nombre><apellidos>VIDAL BRAVO</apellidos><email>avidalbravo@iesvdc.com</email><numeroDNI>86147250</numeroDNI><letraDNI>Z</letraDNI><fechaNacimiento>1976-12-23</fechaNacimiento><sexo>PND</sexo></personas><personas><nombre>ALVARO</nombre><apellidos>LORENZO MEDINA</apellidos><email>alorenzomedina@iesvdc.com</email><numeroDNI>60805781</numeroDNI><letraDNI>Z</letraDNI><fechaNacimiento>1925-11-14</fechaNacimiento><sexo>HOMBRE</sexo></personas><personas><nombre>ALFREDO</nombre><apellidos>CORTES VELASCO</apellidos><email>acortesvelasco@iesvdc.com</email><numeroDNI>42018464</numeroDNI><letraDNI>V</letraDNI><fechaNacimiento>1946-09-17</fechaNacimiento><sexo>PND</sexo></personas><personas><nombre>OSCAR</nombre><apellidos>PASTOR ALONSO</apellidos><email>opastoralonso@iesvdc.com</email><numeroDNI>79591094</numeroDNI><letraDNI>P</letraDNI><fechaNacimiento>1949-06-10</fechaNacimiento><sexo>PND</sexo></personas><personas><nombre>ANTONIO</nombre><apellidos>VEGA PRIETO</apellidos><email>avegaprieto@iesvdc.com</email><numeroDNI>71223644</numeroDNI><letraDNI>G</letraDNI><fechaNacimiento>1922-07-25</fechaNacimiento><sexo>MUJER</sexo></personas><personas><nombre>JOSE LUIS</nombre><apellidos>JIMENEZ VEGA</apellidos><email>jjimenezvega@iesvdc.com</email><numeroDNI>34978866</numeroDNI><letraDNI>Y</letraDNI><fechaNacimiento>2017-06-28</fechaNacimiento><sexo>MUJER</sexo></personas><personas><nombre>FRANCISCO</nombre><apellidos>VEGA HERRERA</apellidos><email>fvegaherrera@iesvdc.com</email><numeroDNI>18321638</numeroDNI><letraDNI>E</letraDNI><fechaNacimiento>2018-09-19</fechaNacimiento><sexo>MUJER</sexo></personas><personas><nombre>DIEGO</nombre><apellidos>CALVO JIMENEZ</apellidos><email>dcalvojimenez@iesvdc.com</email><numeroDNI>45795325</numeroDNI><letraDNI>W</letraDNI><fechaNacimiento>2015-10-15</fechaNacimiento><sexo>HOMBRE</sexo></personas><personas><nombre>ALBERT</nombre><apellidos>RAMOS SERRANO</apellidos><email>aramosserrano@iesvdc.com</email><numeroDNI>87963903</numeroDNI><letraDNI>N</letraDNI><fechaNacimiento>2007-01-31</fechaNacimiento><sexo>PND</sexo></personas><personas><nombre>JUAN MANUEL</nombre><apellidos>IBAÑEZ CAMPOS</apellidos><email>jibanezcampos@iesvdc.com</email><numeroDNI>42864817</numeroDNI><letraDNI>Q</letraDNI><fechaNacimiento>1998-02-11</fechaNacimiento><sexo>HOMBRE</sexo></personas></personas>